pi_finder/__init__.py
pi_finder/main.py
pi_finder-0.1.1.dist-info/entry_points.txt
pi_finder-0.1.1.dist-info/WHEEL
pi_finder-0.1.1.dist-info/METADATA
pi_finder-0.1.1.dist-info/RECORD
